{
  "toolsetVersion": "2026.02",
  "rids": {
    "win-x64": {
      "ffmpeg": {
        "version": "8.0.1",
        "expectedSha256": "a0c715acca3839bfd203e600a7775b83cfe3ff928a4eceb9ca54f2982365901c",
        "archiveUrl": "https://github.com/GyanD/codexffmpeg/releases/download/8.0.1/ffmpeg-8.0.1-essentials_build.7z",
        "archiveType": "7z",
        "extractMap": {
          "ffmpeg.exe": "bin/ffmpeg.exe",
          "ffprobe.exe": "bin/ffprobe.exe"
        }
      },
      "mkvtoolnix": {
        "version": "97.0",
        "expectedSha256": "0000000000000000000000000000000000000000000000000000000000000000",
        "archiveUrl": "https://mkvtoolnix.download/windows/releases/97.0/mkvtoolnix-64-bit-97.0.7z",
        "sha256Url": "https://mkvtoolnix.download/windows/releases/97.0/sha256sums.txt",
        "sha256Entry": "mkvtoolnix-64-bit-97.0.7z",
        "archiveType": "7z",
        "extractMap": {
          "mkvmerge.exe": "mkvmerge.exe",
          "mkvpropedit.exe": "mkvpropedit.exe"
        }
      },
      "mediainfo": {
        "version": "25.10",
        "expectedSha256": "e47978091e5716052409d776cafbd42819a17dc9ab4586f413faf60c82d39c92",
        "archiveUrl": "https://mediaarea.net/download/binary/mediainfo/25.10/MediaInfo_CLI_25.10_Windows_x64.zip",
        "archiveType": "zip",
        "extractMap": {
          "mediainfo.exe": "mediainfo.exe"
        }
      }
    }
  }
}
